cfgpy
