Metadata-Version: 1.0
Name: cfgpy
Version: 1.0.3
Summary: A simple, flexible, and powerful config reader for Python
Home-page: https://github.com/phenicle/cfgpy
Author: Phenicle
Author-email: pheniclebeefheart@gmail.com
License: Mozilla Public License 2.0 (MPL 2.0)
Platform: UNKNOWN
